pytrec_eval_ext.cp310-win_amd64.pyd
pytrec_eval/__init__.py
pytrec_eval/py.typed
pytrec_eval_terrier-0.5.10.dist-info/licenses/LICENSE
pytrec_eval_terrier-0.5.10.dist-info/METADATA
pytrec_eval_terrier-0.5.10.dist-info/WHEEL
pytrec_eval_terrier-0.5.10.dist-info/top_level.txt
pytrec_eval_terrier-0.5.10.dist-info/RECORD
